json_toolkit/__init__.py
json_toolkit/manipulator.py
json_toolkit-0.2.2.dist-info/LICENSE
json_toolkit-0.2.2.dist-info/METADATA
json_toolkit-0.2.2.dist-info/WHEEL
json_toolkit-0.2.2.dist-info/top_level.txt
json_toolkit-0.2.2.dist-info/RECORD
