Metadata-Version: 2.1
Name: json-toolkit
Version: 0.2.2
Summary: A simple library for JSON manipulation
Home-page: https://github.com/S1lentAFK/json-toolkit
Author: o_frun
Classifier: Programming Language :: Python :: 3
Classifier: License :: OSI Approved :: MIT License
Classifier: Operating System :: OS Independent
Requires-Python: >=3.6
License-File: LICENSE
